packinit/__init__.py
packinit/core.py
packinit/extra_files/__init__.py
packinit/extra_files/log4j2.xml
packinit/utils.py
packinit-0.3.3.dist-info/entry_points.txt
packinit-0.3.3.dist-info/LICENSE.rst
packinit-0.3.3.dist-info/WHEEL
packinit-0.3.3.dist-info/METADATA
packinit-0.3.3.dist-info/RECORD
